colordemo-0.3.0.dist-info/METADATA
colordemo-0.3.0.dist-info/WHEEL
colordemo-0.3.0.dist-info/entry_points.txt
colordemo-0.3.0.dist-info/licenses/COPYING
colordemo/__init__.py
colordemo/__main__.py
colordemo/color_display.py
colordemo/colors.py
colordemo/terminal_query.py
colordemo-0.3.0.dist-info/RECORD
