Metadata-Version: 2.1
Name: colordemo
Version: 0.3.0
Summary: RGB queries on xterm-like terminals
Author-Email: Darsh Ranjan <dranjan@berkeley.edu>
License:                     GNU GENERAL PUBLIC LICENSE
Classifier: Development Status :: 4 - Beta
Classifier: License :: OSI Approved :: GNU General Public License v3 or later (GPLv3+)
Classifier: Operating System :: OS Independent
Classifier: Programming Language :: Python :: 3
Project-URL: Homepage, https://github.com/dranjan/python-colordemo
Project-URL: Documentation, https://github.com/dranjan/python-colordemo
Project-URL: Repository, https://github.com/dranjan/python-colordemo
Requires-Python: >=3.0
